{
	"cidades": [
		{
			"id": 1,
			"name": "Alfredo Vasconcelos"
		},
		{
			"id": 2,
			"name": "Antônio Carlos"
		},
		{
			"id": 3,
			"name": "Barbacena"
		},
		{
			"id": 4,
			"name": "Barroso"
		},
		{
			"id": 5,
			"name": "Capela Nova"
		},
		{
			"id": 6,
			"name": "Caranaíba"
		},
		{
			"id": 7,
			"name": "Carandaí"
		},
		{
			"id": 8,
			"name": "Desterro do Melo"
		},
		{
			"id": 9,
			"name": "Ibertioga"
		},
		{
			"id": 10,
			"name": "Ressaquinha"
		},
		{
			"id": 11,
			"name": "Santa Bárbara do Tugúrio"
		},
		{
			"id": 12,
			"name": "Carrancas"
		},
		{
			"id": 13,
			"name": "Ijaci"
		},
		{
			"id": 14,
			"name": "Ingaí"
		},
		{
			"id": 15,
			"name": "Itumirim"
		}
	]
}

